resilient_logger/__init__.py
resilient_logger/admin.py
resilient_logger/apps.py
resilient_logger/handlers.py
resilient_logger/resilient_logger.py
resilient_logger/utils.py
resilient_logger/errors/__init__.py
resilient_logger/errors/missing_context_error.py
resilient_logger/management/__init__.py
resilient_logger/management/commands/__init__.py
resilient_logger/management/commands/clear_sent_entries.py
resilient_logger/management/commands/submit_unsent_entries.py
resilient_logger/migrations/0001_initial.py
resilient_logger/migrations/0002_alter_verbose_name.py
resilient_logger/migrations/0003_created_at_sorting_and_index.py
resilient_logger/migrations/0004_remove_explicit_id.py
resilient_logger/migrations/__init__.py
resilient_logger/models/__init__.py
resilient_logger/models/resilient_log_entry.py
resilient_logger/sources/__init__.py
resilient_logger/sources/abstract_log_source.py
resilient_logger/sources/django_audit_log_source.py
resilient_logger/sources/resilient_log_source.py
resilient_logger/targets/__init__.py
resilient_logger/targets/abstract_log_target.py
resilient_logger/targets/elasticsearch_log_target.py
resilient_logger/targets/proxy_log_target.py
django_resilient_logger-1.2.0.dist-info/METADATA
django_resilient_logger-1.2.0.dist-info/WHEEL
django_resilient_logger-1.2.0.dist-info/licenses/LICENSE
django_resilient_logger-1.2.0.dist-info/RECORD
