Metadata-Version: 2.4
Name: django-resilient-logger
Version: 1.2.0
Summary: A module that provides django-specific resilient logger module.
Project-URL: Homepage, https://github.com/City-of-Helsinki/django-resilient-logger
Project-URL: Issues, https://github.com/City-of-Helsinki/django-resilient-logger/issues
Author-email: City of Helsinki <dev@hel.fi>
License-Expression: MIT
License-File: LICENSE
Keywords: django,logging,plugin extension
Classifier: Environment :: Web Environment
Classifier: Framework :: Django
Classifier: Framework :: Django :: 4.2
Classifier: Framework :: Django :: 5.1
Classifier: Framework :: Django :: 5.2
Classifier: Intended Audience :: Developers
Classifier: Operating System :: OS Independent
Classifier: Programming Language :: Python
Classifier: Programming Language :: Python :: 3
Classifier: Programming Language :: Python :: 3 :: Only
Classifier: Programming Language :: Python :: 3.10
Classifier: Programming Language :: Python :: 3.11
Classifier: Programming Language :: Python :: 3.12
Classifier: Programming Language :: Python :: 3.13
Classifier: Programming Language :: Python :: 3.14
Classifier: Topic :: Internet :: WWW/HTTP
Classifier: Topic :: Internet :: WWW/HTTP :: Dynamic Content
Requires-Dist: django>=4.2
Requires-Dist: elasticsearch8
Provides-Extra: all
Requires-Dist: coverage-enable-subprocess; extra == 'all'
Requires-Dist: coverage[toml]; extra == 'all'
Requires-Dist: django-auditlog; extra == 'all'
Requires-Dist: pytest; extra == 'all'
Requires-Dist: pytest-django; extra == 'all'
Requires-Dist: pytest-randomly; extra == 'all'
Requires-Dist: pytest-rerunfailures; extra == 'all'
Requires-Dist: pytest-xdist[psutil]; extra == 'all'
Provides-Extra: auditlog
Requires-Dist: django-auditlog; extra == 'auditlog'
Provides-Extra: test
Requires-Dist: coverage-enable-subprocess; extra == 'test'
Requires-Dist: coverage[toml]; extra == 'test'
Requires-Dist: pytest; extra == 'test'
Requires-Dist: pytest-django; extra == 'test'
Requires-Dist: pytest-randomly; extra == 'test'
Requires-Dist: pytest-rerunfailures; extra == 'test'
Requires-Dist: pytest-xdist[psutil]; extra == 'test'
